{
    "extension": "linecount",
    "version": "0.1.7",
    "workspace": "c:\\Users\\El Senor\\OneDrive - Colorado Springs School District 11\\da-lern-place",
    "linecount": [
        {
            "version": "0.1.7",
            "counttime": "2019-02-15 19:14:28",
            "filesum": 125,
            "codesum": 15946,
            "commentsum": 1769,
            "blanksum": 3216,
            "filelist": [
                {
                    "blank": 353,
                    "code": 1881,
                    "comment": 29,
                    "filename": "Coronado High School _ Homepage.html"
                },
                {
                    "filename": "Coronado High School _ Homepage_files\\120x240recad1.jpg",
                    "isbinaryfile": true,
                    "blank": 0,
                    "code": 0,
                    "comment": 0
                },
                {
                    "filename": "Coronado High School _ Homepage_files\\2019-01-17 11.13.24.jpg",
                    "isbinaryfile": true,
                    "blank": 0,
                    "code": 0,
                    "comment": 0
                },
                {
                    "filename": "Coronado High School _ Homepage_files\\2019-01-17 18.42.55.jpg",
                    "isbinaryfile": true,
                    "blank": 0,
                    "code": 0,
                    "comment": 0
                },
                {
                    "filename": "Coronado High School _ Homepage_files\\adams.png",
                    "isbinaryfile": true,
                    "blank": 0,
                    "code": 0,
                    "comment": 0
                },
                {
                    "blank": 0,
                    "code": 1,
                    "comment": 0,
                    "filename": "Coronado High School _ Homepage_files\\ally.1b07f5b730104dc17d0324bd633e8ab9.css"
                },
                {
                    "blank": 0,
                    "code": 1,
                    "comment": 1,
                    "filename": "Coronado High School _ Homepage_files\\ally.ui.5f50f96bdc8f4ccc378b.js.download"
                },
                {
                    "blank": 11,
                    "code": 38,
                    "comment": 16,
                    "filename": "Coronado High School _ Homepage_files\\ally.ui.js.download"
                },
                {
                    "blank": 53,
                    "code": 257,
                    "comment": 81,
                    "filename": "Coronado High School _ Homepage_files\\API.js.download"
                },
                {
                    "blank": 233,
                    "code": 1550,
                    "comment": 126,
                    "filename": "Coronado High School _ Homepage_files\\apps.css"
                },
                {
                    "filename": "Coronado High School _ Homepage_files\\asu.png",
                    "isbinaryfile": true,
                    "blank": 0,
                    "code": 0,
                    "comment": 0
                },
                {
                    "filename": "Coronado High School _ Homepage_files\\aub.png",
                    "isbinaryfile": true,
                    "blank": 0,
                    "code": 0,
                    "comment": 0
                },
                {
                    "filename": "Coronado High School _ Homepage_files\\az.png",
                    "isbinaryfile": true,
                    "blank": 0,
                    "code": 0,
                    "comment": 0
                },
                {
                    "filename": "Coronado High School _ Homepage_files\\bay.png",
                    "isbinaryfile": true,
                    "blank": 0,
                    "code": 0,
                    "comment": 0
                },
                {
                    "filename": "Coronado High School _ Homepage_files\\blackboard_logo.png",
                    "isbinaryfile": true,
                    "blank": 0,
                    "code": 0,
                    "comment": 0
                },
                {
                    "filename": "Coronado High School _ Homepage_files\\bowling.jpg",
                    "isbinaryfile": true,
                    "blank": 0,
                    "code": 0,
                    "comment": 0
                },
                {
                    "filename": "Coronado High School _ Homepage_files\\byu.png",
                    "isbinaryfile": true,
                    "blank": 0,
                    "code": 0,
                    "comment": 0
                },
                {
                    "filename": "Coronado High School _ Homepage_files\\cal.jpg",
                    "isbinaryfile": true,
                    "blank": 0,
                    "code": 0,
                    "comment": 0
                },
                {
                    "filename": "Coronado High School _ Homepage_files\\cc.png",
                    "isbinaryfile": true,
                    "blank": 0,
                    "code": 0,
                    "comment": 0
                },
                {
                    "blank": 3,
                    "code": 152,
                    "comment": 12,
                    "filename": "Coronado High School _ Homepage_files\\CheckScript.js.download"
                },
                {
                    "filename": "Coronado High School _ Homepage_files\\coe.jpg",
                    "isbinaryfile": true,
                    "blank": 0,
                    "code": 0,
                    "comment": 0
                },
                {
                    "filename": "Coronado High School _ Homepage_files\\colorado christian.png",
                    "isbinaryfile": true,
                    "blank": 0,
                    "code": 0,
                    "comment": 0
                },
                {
                    "filename": "Coronado High School _ Homepage_files\\columbia.png",
                    "isbinaryfile": true,
                    "blank": 0,
                    "code": 0,
                    "comment": 0
                },
                {
                    "filename": "Coronado High School _ Homepage_files\\cornell.png",
                    "isbinaryfile": true,
                    "blank": 0,
                    "code": 0,
                    "comment": 0
                },
                {
                    "filename": "Coronado High School _ Homepage_files\\Coronado.png",
                    "isbinaryfile": true,
                    "blank": 0,
                    "code": 0,
                    "comment": 0
                },
                {
                    "blank": 1,
                    "code": 1,
                    "comment": 3,
                    "filename": "Coronado High School _ Homepage_files\\creative.accessible.navigation.app.min.js.download"
                },
                {
                    "blank": 1,
                    "code": 1,
                    "comment": 3,
                    "filename": "Coronado High School _ Homepage_files\\creative.responsive.menu.v2.min.js.download"
                },
                {
                    "blank": 1,
                    "code": 1,
                    "comment": 3,
                    "filename": "Coronado High School _ Homepage_files\\creative.responsive.pagelist.menu.v2.min.js.download"
                },
                {
                    "blank": 1,
                    "code": 1,
                    "comment": 3,
                    "filename": "Coronado High School _ Homepage_files\\creative.translate.min.js.download"
                },
                {
                    "blank": 1,
                    "code": 1,
                    "comment": 5,
                    "filename": "Coronado High School _ Homepage_files\\creativeIcons.min.css"
                },
                {
                    "blank": 1,
                    "code": 1,
                    "comment": 2,
                    "filename": "Coronado High School _ Homepage_files\\creativeIcons.v3.min.js.download"
                },
                {
                    "filename": "Coronado High School _ Homepage_files\\crei.jpg",
                    "isbinaryfile": true,
                    "blank": 0,
                    "code": 0,
                    "comment": 0
                },
                {
                    "blank": 1,
                    "code": 1,
                    "comment": 5,
                    "filename": "Coronado High School _ Homepage_files\\cs.global.min.css"
                },
                {
                    "blank": 1,
                    "code": 1,
                    "comment": 3,
                    "filename": "Coronado High School _ Homepage_files\\cs.global.min.js.download"
                },
                {
                    "blank": 1,
                    "code": 1,
                    "comment": 3,
                    "filename": "Coronado High School _ Homepage_files\\cs.rs.photo.gallery.rotator.min.js.download"
                },
                {
                    "blank": 0,
                    "code": 308,
                    "comment": 88,
                    "filename": "Coronado High School _ Homepage_files\\css"
                },
                {
                    "filename": "Coronado High School _ Homepage_files\\csu.jpg",
                    "isbinaryfile": true,
                    "blank": 0,
                    "code": 0,
                    "comment": 0
                },
                {
                    "filename": "Coronado High School _ Homepage_files\\ctu.png",
                    "isbinaryfile": true,
                    "blank": 0,
                    "code": 0,
                    "comment": 0
                },
                {
                    "filename": "Coronado High School _ Homepage_files\\cu.png",
                    "isbinaryfile": true,
                    "blank": 0,
                    "code": 0,
                    "comment": 0
                },
                {
                    "filename": "Coronado High School _ Homepage_files\\cuden.png",
                    "isbinaryfile": true,
                    "blank": 0,
                    "code": 0,
                    "comment": 0
                },
                {
                    "blank": 441,
                    "code": 2417,
                    "comment": 275,
                    "filename": "Coronado High School _ Homepage_files\\dashboard.css"
                },
                {
                    "filename": "Coronado High School _ Homepage_files\\doane.png",
                    "isbinaryfile": true,
                    "blank": 0,
                    "code": 0,
                    "comment": 0
                },
                {
                    "blank": 13,
                    "code": 194,
                    "comment": 24,
                    "filename": "Coronado High School _ Homepage_files\\drt-default-css.css"
                },
                {
                    "filename": "Coronado High School _ Homepage_files\\du.png",
                    "isbinaryfile": true,
                    "blank": 0,
                    "code": 0,
                    "comment": 0
                },
                {
                    "filename": "Coronado High School _ Homepage_files\\emb.png",
                    "isbinaryfile": true,
                    "blank": 0,
                    "code": 0,
                    "comment": 0
                },
                {
                    "filename": "Coronado High School _ Homepage_files\\Facebook.png",
                    "isbinaryfile": true,
                    "blank": 0,
                    "code": 0,
                    "comment": 0
                },
                {
                    "filename": "Coronado High School _ Homepage_files\\fl.png",
                    "isbinaryfile": true,
                    "blank": 0,
                    "code": 0,
                    "comment": 0
                },
                {
                    "filename": "Coronado High School _ Homepage_files\\ft lewis.png",
                    "isbinaryfile": true,
                    "blank": 0,
                    "code": 0,
                    "comment": 0
                },
                {
                    "blank": 7,
                    "code": 250,
                    "comment": 2,
                    "filename": "Coronado High School _ Homepage_files\\galleria.classic.css"
                },
                {
                    "blank": 29,
                    "code": 132,
                    "comment": 21,
                    "filename": "Coronado High School _ Homepage_files\\galleria.classic.min.js.download"
                },
                {
                    "blank": 0,
                    "code": 1,
                    "comment": 0,
                    "filename": "Coronado High School _ Homepage_files\\gpt.js.download"
                },
                {
                    "blank": 328,
                    "code": 1163,
                    "comment": 2,
                    "filename": "Coronado High School _ Homepage_files\\Grid.css"
                },
                {
                    "filename": "Coronado High School _ Homepage_files\\harv.png",
                    "isbinaryfile": true,
                    "blank": 0,
                    "code": 0,
                    "comment": 0
                },
                {
                    "filename": "Coronado High School _ Homepage_files\\harvey.png",
                    "isbinaryfile": true,
                    "blank": 0,
                    "code": 0,
                    "comment": 0
                },
                {
                    "filename": "Coronado High School _ Homepage_files\\hastings.jpg",
                    "isbinaryfile": true,
                    "blank": 0,
                    "code": 0,
                    "comment": 0
                },
                {
                    "blank": 0,
                    "code": 4,
                    "comment": 5,
                    "filename": "Coronado High School _ Homepage_files\\head.min.js.download"
                },
                {
                    "blank": 205,
                    "code": 982,
                    "comment": 117,
                    "filename": "Coronado High School _ Homepage_files\\Initialize.js.download"
                },
                {
                    "filename": "Coronado High School _ Homepage_files\\ith.png",
                    "isbinaryfile": true,
                    "blank": 0,
                    "code": 0,
                    "comment": 0
                },
                {
                    "blank": 1,
                    "code": 1,
                    "comment": 3,
                    "filename": "Coronado High School _ Homepage_files\\jacinda.viewFullSite.min.js.download"
                },
                {
                    "filename": "Coronado High School _ Homepage_files\\jbu.png",
                    "isbinaryfile": true,
                    "blank": 0,
                    "code": 0,
                    "comment": 0
                },
                {
                    "blank": 0,
                    "code": 1,
                    "comment": 0,
                    "filename": "Coronado High School _ Homepage_files\\joel.mod-events.min.js.download"
                },
                {
                    "filename": "Coronado High School _ Homepage_files\\jos.png",
                    "isbinaryfile": true,
                    "blank": 0,
                    "code": 0,
                    "comment": 0
                },
                {
                    "blank": 0,
                    "code": 2,
                    "comment": 0,
                    "filename": "Coronado High School _ Homepage_files\\jquery-migrate-1.2.1.js.download"
                },
                {
                    "blank": 0,
                    "code": 1,
                    "comment": 4,
                    "filename": "Coronado High School _ Homepage_files\\jquery-ui.min.js.download"
                },
                {
                    "blank": 0,
                    "code": 1,
                    "comment": 0,
                    "filename": "Coronado High School _ Homepage_files\\jquery.ajaxupload.min.js.download"
                },
                {
                    "blank": 19,
                    "code": 97,
                    "comment": 3,
                    "filename": "Coronado High School _ Homepage_files\\jquery.jgrowl.css"
                },
                {
                    "blank": 0,
                    "code": 3,
                    "comment": 4,
                    "filename": "Coronado High School _ Homepage_files\\jquery.min.js.download"
                },
                {
                    "blank": 84,
                    "code": 357,
                    "comment": 30,
                    "filename": "Coronado High School _ Homepage_files\\jquery.sectionlayer.js.download"
                },
                {
                    "blank": 30,
                    "code": 137,
                    "comment": 56,
                    "filename": "Coronado High School _ Homepage_files\\jQueryUI.css"
                },
                {
                    "blank": 11,
                    "code": 25,
                    "comment": 156,
                    "filename": "Coronado High School _ Homepage_files\\json2.js.download"
                },
                {
                    "filename": "Coronado High School _ Homepage_files\\Kaleb Rinck Digital Music Production Prodigy.jpg",
                    "isbinaryfile": true,
                    "blank": 0,
                    "code": 0,
                    "comment": 0
                },
                {
                    "filename": "Coronado High School _ Homepage_files\\kan.png",
                    "isbinaryfile": true,
                    "blank": 0,
                    "code": 0,
                    "comment": 0
                },
                {
                    "filename": "Coronado High School _ Homepage_files\\ku.png",
                    "isbinaryfile": true,
                    "blank": 0,
                    "code": 0,
                    "comment": 0
                },
                {
                    "filename": "Coronado High School _ Homepage_files\\lc.jpg",
                    "isbinaryfile": true,
                    "blank": 0,
                    "code": 0,
                    "comment": 0
                },
                {
                    "filename": "Coronado High School _ Homepage_files\\loy.png",
                    "isbinaryfile": true,
                    "blank": 0,
                    "code": 0,
                    "comment": 0
                },
                {
                    "filename": "Coronado High School _ Homepage_files\\mesa.png",
                    "isbinaryfile": true,
                    "blank": 0,
                    "code": 0,
                    "comment": 0
                },
                {
                    "filename": "Coronado High School _ Homepage_files\\metro.jpg",
                    "isbinaryfile": true,
                    "blank": 0,
                    "code": 0,
                    "comment": 0
                },
                {
                    "filename": "Coronado High School _ Homepage_files\\mines.jpg",
                    "isbinaryfile": true,
                    "blank": 0,
                    "code": 0,
                    "comment": 0
                },
                {
                    "filename": "Coronado High School _ Homepage_files\\miss.png",
                    "isbinaryfile": true,
                    "blank": 0,
                    "code": 0,
                    "comment": 0
                },
                {
                    "filename": "Coronado High School _ Homepage_files\\mountain.png",
                    "isbinaryfile": true,
                    "blank": 0,
                    "code": 0,
                    "comment": 0
                },
                {
                    "filename": "Coronado High School _ Homepage_files\\nm.png",
                    "isbinaryfile": true,
                    "blank": 0,
                    "code": 0,
                    "comment": 0
                },
                {
                    "filename": "Coronado High School _ Homepage_files\\noaz.png",
                    "isbinaryfile": true,
                    "blank": 0,
                    "code": 0,
                    "comment": 0
                },
                {
                    "filename": "Coronado High School _ Homepage_files\\notre.jpg",
                    "isbinaryfile": true,
                    "blank": 0,
                    "code": 0,
                    "comment": 0
                },
                {
                    "filename": "Coronado High School _ Homepage_files\\nwu.jpg",
                    "isbinaryfile": true,
                    "blank": 0,
                    "code": 0,
                    "comment": 0
                },
                {
                    "filename": "Coronado High School _ Homepage_files\\nyu.jpg",
                    "isbinaryfile": true,
                    "blank": 0,
                    "code": 0,
                    "comment": 0
                },
                {
                    "blank": 0,
                    "code": 9,
                    "comment": 0,
                    "filename": "Coronado High School _ Homepage_files\\OpenSans-Italic.css"
                },
                {
                    "blank": 0,
                    "code": 8,
                    "comment": 0,
                    "filename": "Coronado High School _ Homepage_files\\OpenSans-Light.css"
                },
                {
                    "blank": 0,
                    "code": 9,
                    "comment": 0,
                    "filename": "Coronado High School _ Homepage_files\\OpenSans-Regular.css"
                },
                {
                    "blank": 1,
                    "code": 9,
                    "comment": 0,
                    "filename": "Coronado High School _ Homepage_files\\OpenSans-SemiBold.css"
                },
                {
                    "filename": "Coronado High School _ Homepage_files\\ou.png",
                    "isbinaryfile": true,
                    "blank": 0,
                    "code": 0,
                    "comment": 0
                },
                {
                    "filename": "Coronado High School _ Homepage_files\\oxy.png",
                    "isbinaryfile": true,
                    "blank": 0,
                    "code": 0,
                    "comment": 0
                },
                {
                    "filename": "Coronado High School _ Homepage_files\\PeachJar.png",
                    "isbinaryfile": true,
                    "blank": 0,
                    "code": 0,
                    "comment": 0
                },
                {
                    "filename": "Coronado High School _ Homepage_files\\ppcc.png",
                    "isbinaryfile": true,
                    "blank": 0,
                    "code": 0,
                    "comment": 0
                },
                {
                    "filename": "Coronado High School _ Homepage_files\\pratt.jpg",
                    "isbinaryfile": true,
                    "blank": 0,
                    "code": 0,
                    "comment": 0
                },
                {
                    "filename": "Coronado High School _ Homepage_files\\pueblo.png",
                    "isbinaryfile": true,
                    "blank": 0,
                    "code": 0,
                    "comment": 0
                },
                {
                    "filename": "Coronado High School _ Homepage_files\\pug.png",
                    "isbinaryfile": true,
                    "blank": 0,
                    "code": 0,
                    "comment": 0
                },
                {
                    "filename": "Coronado High School _ Homepage_files\\purd.png",
                    "isbinaryfile": true,
                    "blank": 0,
                    "code": 0,
                    "comment": 0
                },
                {
                    "filename": "Coronado High School _ Homepage_files\\qlogo37.png",
                    "isbinaryfile": true,
                    "blank": 0,
                    "code": 0,
                    "comment": 0
                },
                {
                    "filename": "Coronado High School _ Homepage_files\\regis.png",
                    "isbinaryfile": true,
                    "blank": 0,
                    "code": 0,
                    "comment": 0
                },
                {
                    "blank": 181,
                    "code": 558,
                    "comment": 2,
                    "filename": "Coronado High School _ Homepage_files\\SchoolwiresMobile_2310.css"
                },
                {
                    "filename": "Coronado High School _ Homepage_files\\sd.png",
                    "isbinaryfile": true,
                    "blank": 0,
                    "code": 0,
                    "comment": 0
                },
                {
                    "blank": 4,
                    "code": 208,
                    "comment": 0,
                    "filename": "Coronado High School _ Homepage_files\\shepherd-theme-default.css"
                },
                {
                    "blank": 0,
                    "code": 1,
                    "comment": 0,
                    "filename": "Coronado High School _ Homepage_files\\shepherd.min.js.download"
                },
                {
                    "filename": "Coronado High School _ Homepage_files\\sou.png",
                    "isbinaryfile": true,
                    "blank": 0,
                    "code": 0,
                    "comment": 0
                },
                {
                    "blank": 0,
                    "code": 1,
                    "comment": 0,
                    "filename": "Coronado High School _ Homepage_files\\sri-failover.min.js.download"
                },
                {
                    "filename": "Coronado High School _ Homepage_files\\sta.png",
                    "isbinaryfile": true,
                    "blank": 0,
                    "code": 0,
                    "comment": 0
                },
                {
                    "filename": "Coronado High School _ Homepage_files\\submit-tip.png",
                    "isbinaryfile": true,
                    "blank": 0,
                    "code": 0,
                    "comment": 0
                },
                {
                    "blank": 1,
                    "code": 1,
                    "comment": 5,
                    "filename": "Coronado High School _ Homepage_files\\sw-icon-library.min.css"
                },
                {
                    "blank": 7,
                    "code": 41,
                    "comment": 8,
                    "filename": "Coronado High School _ Homepage_files\\SW-UI.min.js.download"
                },
                {
                    "blank": 0,
                    "code": 1,
                    "comment": 3,
                    "filename": "Coronado High School _ Homepage_files\\swfobject.js.download"
                },
                {
                    "blank": 0,
                    "code": 1,
                    "comment": 0,
                    "filename": "Coronado High School _ Homepage_files\\swfobject.min.js.download"
                },
                {
                    "blank": 1153,
                    "code": 4898,
                    "comment": 633,
                    "filename": "Coronado High School _ Homepage_files\\system.css"
                },
                {
                    "filename": "Coronado High School _ Homepage_files\\tcu.png",
                    "isbinaryfile": true,
                    "blank": 0,
                    "code": 0,
                    "comment": 0
                },
                {
                    "blank": 0,
                    "code": 1,
                    "comment": 0,
                    "filename": "Coronado High School _ Homepage_files\\tether.min.js.download"
                },
                {
                    "filename": "Coronado High School _ Homepage_files\\ubc.png",
                    "isbinaryfile": true,
                    "blank": 0,
                    "code": 0,
                    "comment": 0
                },
                {
                    "filename": "Coronado High School _ Homepage_files\\uccs.png",
                    "isbinaryfile": true,
                    "blank": 0,
                    "code": 0,
                    "comment": 0
                },
                {
                    "filename": "Coronado High School _ Homepage_files\\unc.jpg",
                    "isbinaryfile": true,
                    "blank": 0,
                    "code": 0,
                    "comment": 0
                },
                {
                    "filename": "Coronado High School _ Homepage_files\\uoa.png",
                    "isbinaryfile": true,
                    "blank": 0,
                    "code": 0,
                    "comment": 0
                },
                {
                    "filename": "Coronado High School _ Homepage_files\\usafa.png",
                    "isbinaryfile": true,
                    "blank": 0,
                    "code": 0,
                    "comment": 0
                },
                {
                    "blank": 39,
                    "code": 235,
                    "comment": 33,
                    "filename": "Coronado High School _ Homepage_files\\WCM.js.download"
                },
                {
                    "filename": "Coronado High School _ Homepage_files\\western.png",
                    "isbinaryfile": true,
                    "blank": 0,
                    "code": 0,
                    "comment": 0
                },
                {
                    "filename": "Coronado High School _ Homepage_files\\wpi.png",
                    "isbinaryfile": true,
                    "blank": 0,
                    "code": 0,
                    "comment": 0
                },
                {
                    "filename": "Coronado High School _ Homepage_files\\wres.jpg",
                    "isbinaryfile": true,
                    "blank": 0,
                    "code": 0,
                    "comment": 0
                },
                {
                    "filename": "Coronado High School _ Homepage_files\\wyo.png",
                    "isbinaryfile": true,
                    "blank": 0,
                    "code": 0,
                    "comment": 0
                },
                {
                    "filename": "Coronado High School _ Homepage_files\\yearbook ad 2.jpg",
                    "isbinaryfile": true,
                    "blank": 0,
                    "code": 0,
                    "comment": 0
                }
            ]
        }
    ]
}